{
  "last_updated": "2026-04-20T23:06:08.000Z",
  "current_readings": {
    "timestamp": "2026-04-20T23:06:08.000Z",
    "facility": {
      "modulesOnline": 24,
      "modulesOffline": 5,
      "activeAlerts": 0,
      "totalAlerts": 8,
      "offlineModules": [
        "Clone Nutrient Module",
        "Clone Room Environment Module ",
        "Environment Module 2",
        "New F1 PIC",
        "Veg Room PIC "
      ]
    },
    "rooms": {
      "Central Feed System": {
        "Solution Temperature": {
          "value": 64.35,
          "min": 63.3,
          "max": 65.4
        },
        "Solution Float": {
          "value": 56.4,
          "min": 17.2,
          "max": 95.6
        },
        "Solution TDS": {
          "value": 738.5,
          "min": 527.0,
          "max": 950.0
        },
        "Solution pH": {
          "value": 6.4,
          "min": 5.8,
          "max": 6.9
        },
        "None": {
          "value": 0.0,
          "min": 0.0,
          "max": 0.0
        },
        "Substrate EC": {
          "value": 0.08,
          "min": 0.08,
          "max": 0.08
        }
      },
      "Clone": {},
      "Cure Room": {
        "Vapor Pressure Deficit": {
          "value": 0.6,
          "min": 0.6,
          "max": 0.6
        },
        "Ambient Temperature": {
          "value": 60.6,
          "min": 60.6,
          "max": 60.6
        },
        "Ambient Humidity": {
          "value": 68.4,
          "min": 68.4,
          "max": 68.4
        },
        "Ambient CO2": {
          "value": 1029.0,
          "min": 1029.0,
          "max": 1029.0
        }
      },
      "Dry Room": {
        "Ambient Temperature": {
          "value": 59.4,
          "min": 58.6,
          "max": 60.2
        },
        "Vapor Pressure Deficit": {
          "value": 0.83,
          "min": 0.8,
          "max": 0.9
        },
        "Ambient CO2": {
          "value": 678.33,
          "min": 641.0,
          "max": 716.0
        },
        "Ambient Humidity": {
          "value": 53.17,
          "min": 51.6,
          "max": 54.7
        }
      },
      "Flower 1": {
        "Ambient CO2": {
          "value": 1215.33,
          "min": 1211.0,
          "max": 1220.0
        },
        "Ambient Temperature": {
          "value": 78.0,
          "min": 77.9,
          "max": 78.1
        },
        "Ambient Humidity": {
          "value": 54.8,
          "min": 52.3,
          "max": 57.3
        },
        "Substrate EC": {
          "value": 2.65,
          "min": 2.14,
          "max": 3.5
        },
        "Substrate VWC": {
          "value": 46.3,
          "min": 39.8,
          "max": 49.8
        },
        "Vapor Pressure Deficit": {
          "value": 1.5,
          "min": 1.4,
          "max": 1.6
        },
        "Substrate Temperature": {
          "value": 79.44,
          "min": 78.6,
          "max": 80.4
        }
      },
      "Flower 2": {
        "Ambient Humidity": {
          "value": 58.83,
          "min": 58.1,
          "max": 59.6
        },
        "Substrate Temperature": {
          "value": 66.67,
          "min": 66.2,
          "max": 67.3
        },
        "Vapor Pressure Deficit": {
          "value": 0.9,
          "min": 0.9,
          "max": 0.9
        },
        "Substrate VWC": {
          "value": 5.15,
          "min": 0.0,
          "max": 21.6
        },
        "Substrate EC": {
          "value": 0.92,
          "min": 0.0,
          "max": 5.62
        },
        "Ambient CO2": {
          "value": 661.33,
          "min": 634.0,
          "max": 686.0
        },
        "Ambient Temperature": {
          "value": 66.23,
          "min": 65.9,
          "max": 66.6
        }
      },
      "Mom": {
        "Ambient Temperature": {
          "value": 77.5,
          "min": 77.4,
          "max": 77.6
        },
        "Substrate Temperature": {
          "value": 77.05,
          "min": 76.3,
          "max": 77.9
        },
        "Substrate EC": {
          "value": 4.05,
          "min": 2.71,
          "max": 4.99
        },
        "Ambient Humidity": {
          "value": 72.05,
          "min": 69.6,
          "max": 74.5
        },
        "Vapor Pressure Deficit": {
          "value": 0.9,
          "min": 0.8,
          "max": 1.0
        },
        "Ambient CO2": {
          "value": 346.5,
          "min": 315.0,
          "max": 378.0
        },
        "Substrate VWC": {
          "value": 36.82,
          "min": 28.5,
          "max": 50.2
        }
      }
    }
  }
}