{
  "last_updated": "2026-04-13T17:00:06.000Z",
  "current_readings": {
    "timestamp": "2026-04-13T17:00:06.000Z",
    "facility": {
      "modulesOnline": 24,
      "modulesOffline": 4,
      "activeAlerts": 0,
      "totalAlerts": 8,
      "offlineModules": [
        "Clone Nutrient Module",
        "Clone Room Environment Module ",
        "Environment Module 2",
        "Veg Room PIC "
      ]
    },
    "rooms": {
      "Central Feed System": {
        "Solution pH": {
          "value": 6.05,
          "min": 5.7,
          "max": 6.4
        },
        "Solution TDS": {
          "value": 750.0,
          "min": 555.0,
          "max": 945.0
        },
        "Solution Temperature": {
          "value": 67.25,
          "min": 64.4,
          "max": 70.1
        },
        "Solution Float": {
          "value": 56.15,
          "min": 45.4,
          "max": 66.9
        },
        "None": {
          "value": 0.0,
          "min": 0.0,
          "max": 0.0
        },
        "Substrate EC": {
          "value": 1.08,
          "min": 1.08,
          "max": 1.08
        }
      },
      "Clone": {},
      "Cure Room": {
        "Ambient Temperature": {
          "value": 62.0,
          "min": 62.0,
          "max": 62.0
        },
        "Ambient Humidity": {
          "value": 68.1,
          "min": 68.1,
          "max": 68.1
        },
        "Ambient CO2": {
          "value": 879.0,
          "min": 879.0,
          "max": 879.0
        },
        "Vapor Pressure Deficit": {
          "value": 0.6,
          "min": 0.6,
          "max": 0.6
        }
      },
      "Dry Room": {
        "Ambient Temperature": {
          "value": 61.03,
          "min": 60.7,
          "max": 61.4
        },
        "Vapor Pressure Deficit": {
          "value": 1.17,
          "min": 1.1,
          "max": 1.2
        },
        "Ambient CO2": {
          "value": 627.33,
          "min": 604.0,
          "max": 661.0
        },
        "Ambient Humidity": {
          "value": 36.5,
          "min": 36.0,
          "max": 37.0
        }
      },
      "Flower 1": {
        "Substrate Temperature": {
          "value": 81.77,
          "min": 79.0,
          "max": 84.0
        },
        "Ambient Humidity": {
          "value": 69.93,
          "min": 68.5,
          "max": 71.4
        },
        "Ambient Temperature": {
          "value": 80.53,
          "min": 78.1,
          "max": 83.0
        },
        "Substrate EC": {
          "value": 3.65,
          "min": 2.6,
          "max": 5.09
        },
        "Ambient CO2": {
          "value": 1206.67,
          "min": 1198.0,
          "max": 1216.0
        },
        "Substrate VWC": {
          "value": 44.86,
          "min": 31.2,
          "max": 50.6
        },
        "Vapor Pressure Deficit": {
          "value": 1.07,
          "min": 0.9,
          "max": 1.2
        }
      },
      "Flower 2": {
        "Ambient CO2": {
          "value": 821.33,
          "min": 804.0,
          "max": 839.0
        },
        "Substrate VWC": {
          "value": 6.0,
          "min": 0.0,
          "max": 20.3
        },
        "Substrate EC": {
          "value": 1.95,
          "min": 0.2,
          "max": 4.8
        },
        "Substrate Temperature": {
          "value": 72.46,
          "min": 69.1,
          "max": 76.5
        },
        "Vapor Pressure Deficit": {
          "value": 1.23,
          "min": 1.1,
          "max": 1.4
        },
        "Ambient Humidity": {
          "value": 51.03,
          "min": 48.7,
          "max": 53.2
        },
        "Ambient Temperature": {
          "value": 70.4,
          "min": 67.7,
          "max": 73.1
        }
      },
      "Mom": {
        "Ambient Temperature": {
          "value": 79.2,
          "min": 77.2,
          "max": 81.2
        },
        "Vapor Pressure Deficit": {
          "value": 1.15,
          "min": 1.0,
          "max": 1.3
        },
        "Ambient Humidity": {
          "value": 66.2,
          "min": 65.2,
          "max": 67.2
        },
        "Ambient CO2": {
          "value": 840.5,
          "min": 806.0,
          "max": 875.0
        },
        "Substrate VWC": {
          "value": 52.82,
          "min": 43.2,
          "max": 75.0
        },
        "Substrate Temperature": {
          "value": 78.25,
          "min": 77.7,
          "max": 79.9
        },
        "Substrate EC": {
          "value": 3.64,
          "min": 3.34,
          "max": 4.05
        }
      }
    }
  }
}